reflspeckit/__init__.py
reflspeckit/_errors.py
reflspeckit/data_classes.py
reflspeckit/py.typed
reflspeckit/spec1D/__init__.py
reflspeckit/spec1D/absorption_feature1d.py
reflspeckit/spec1D/continuum_removal.py
reflspeckit/spec1D/filtering.py
reflspeckit/spec1D/outlier_detection.py
reflspeckit/spec1D/polyfit.py
reflspeckit/spec1D/spec1d.py
reflspeckit/spec1D/utils.py
reflspeckit/spec3D/__init__.py
reflspeckit/spec3D/absorption_feature3d.py
reflspeckit/spec3D/continuum_removal.py
reflspeckit/spec3D/filtering.py
reflspeckit/spec3D/outlier_detection.py
reflspeckit/spec3D/polyfit.py
reflspeckit/spec3D/spec3d.py
reflspeckit/spec3D/utils.py
reflspeckit/utils/__init__.py
reflspeckit/utils/get_nonzero.py
reflspeckit/utils/normalize_image.py
reflspeckit/utils/rgb_composite.py
reflspeckit/utils/wvl_search.py
reflspeckit-0.2.0.dist-info/licenses/LICENSE
reflspeckit-0.2.0.dist-info/METADATA
reflspeckit-0.2.0.dist-info/WHEEL
reflspeckit-0.2.0.dist-info/RECORD
