Metadata-Version: 2.4
Name: reflspeckit
Version: 0.2.0
Summary: Utility package for working with spectral data cubes.
License: LICENSE
License-File: LICENSE
Keywords: hyperspectral,processing,spectral cube,image
Author: Z.M. Vig
Author-email: zvig@umd.edu
Requires-Python: >=3.13
Classifier: License :: Other/Proprietary License
Classifier: Programming Language :: Python :: 3
Classifier: Programming Language :: Python :: 3.13
Classifier: Programming Language :: Python :: 3.14
Requires-Dist: astropy (>=7.1.0,<8.0.0)
Requires-Dist: numpy (>=2.2,<3.0)
Requires-Dist: scipy (>=1.16.3,<2.0.0)
Requires-Dist: scipy-stubs (>=1.16.3.0,<2.0.0.0)
Project-URL: Homepage, https://github.com/z-vig/spectralcubekit.git
Project-URL: Repository, https://github.com/z-vig/spectralcubekit.git
